[
  {
    "wallet": "0xc308447bc9ef6e72018a3f3914005bd24c207b09",
    "name": "megacapper",
    "train_win": 75.1,
    "train_conv_roi": 0.112,
    "train_z": 2.52,
    "z_all": 5.24,
    "med_stake": 150,
    "avg_entry": 0.68,
    "train_n": 189,
    "fwd_win": 55.8,
    "fwd_conv_roi": -0.186,
    "fwd_n": 43,
    "conv_win": 69.7,
    "conv_won": 230,
    "conv_lost": 100,
    "conv_ref": 3,
    "conv_sold": 89,
    "conv_pnl": -1028,
    "conv30_win": 90.0,
    "conv30_won": 18,
    "conv30_lost": 2,
    "conv30_ref": 1,
    "conv30_sold": 26,
    "conv30_pnl": 2987,
    "realized_pnl": 20728,
    "all_win": 38.8,
    "all_won": 628,
    "all_lost": 992,
    "all_ref": 32,
    "all_sold": 451,
    "all_pnl": 1466,
    "open_pnl": 7,
    "pm_pnl": 5139,
    "avg_bet": 242,
    "copy_pnl": 4212,
    "held_pnl": -200,
    "held_won": 12,
    "held_lost": 8,
    "sold": 68,
    "last_trade": 1783539388,
    "last_conv_bet": 1783531636,
    "med_lead_h": 3.4,
    "trust_n": 267,
    "trust_wr": 0.689,
    "trust_roi": 0.026,
    "trust_refunds": 0
  },
  {
    "wallet": "0x2d462b29127b919ae4c085e03be44ae7077e3e2d",
    "name": "Vahan88",
    "train_win": 78.3,
    "train_conv_roi": 0.222,
    "train_z": 2.59,
    "z_all": 3.83,
    "med_stake": 355,
    "avg_entry": 0.71,
    "train_n": 166,
    "fwd_win": 65.6,
    "fwd_conv_roi": 0.48,
    "fwd_n": 125,
    "conv_win": 87.8,
    "conv_won": 86,
    "conv_lost": 12,
    "conv_ref": 29,
    "conv_sold": 116,
    "conv_pnl": -2362,
    "conv30_win": 81.5,
    "conv30_won": 22,
    "conv30_lost": 5,
    "conv30_ref": 12,
    "conv30_sold": 30,
    "conv30_pnl": -5232,
    "realized_pnl": 11462,
    "all_win": 43.5,
    "all_won": 276,
    "all_lost": 358,
    "all_ref": 104,
    "all_sold": 473,
    "all_pnl": 21952,
    "open_pnl": 597,
    "pm_pnl": 24306,
    "avg_bet": 742,
    "copy_pnl": 3209,
    "held_pnl": 446,
    "held_won": 25,
    "held_lost": 15,
    "sold": 15,
    "last_trade": 1783528378,
    "last_conv_bet": 1783525454,
    "med_lead_h": 159.3,
    "trust_n": 215,
    "trust_wr": 0.772,
    "trust_roi": 0.245,
    "trust_refunds": 0
  },
  {
    "wallet": "0xd96750bf8d941a8186e592b0ae6e096da66aa266",
    "name": "imwalkinghere",
    "train_win": 76.4,
    "train_conv_roi": 0.353,
    "train_z": 3.75,
    "z_all": 8.06,
    "med_stake": 138,
    "avg_entry": 0.56,
    "train_n": 72,
    "fwd_win": 71.4,
    "fwd_conv_roi": 0.241,
    "fwd_n": 203,
    "conv_win": 71.4,
    "conv_won": 157,
    "conv_lost": 63,
    "conv_ref": 0,
    "conv_sold": 2,
    "conv_pnl": 15967,
    "conv30_win": 93.7,
    "conv30_won": 104,
    "conv30_lost": 7,
    "conv30_ref": 0,
    "conv30_sold": 2,
    "conv30_pnl": 22485,
    "realized_pnl": 28334,
    "all_win": 73.4,
    "all_won": 813,
    "all_lost": 295,
    "all_ref": 0,
    "all_sold": 2,
    "all_pnl": 23432,
    "open_pnl": 0,
    "pm_pnl": 23325,
    "avg_bet": 265,
    "copy_pnl": 2405,
    "held_pnl": 2311,
    "held_won": 76,
    "held_lost": 31,
    "sold": 1,
    "last_trade": 1783526702,
    "last_conv_bet": 1783446002,
    "med_lead_h": 2.2,
    "trust_n": 216,
    "trust_wr": 0.731,
    "trust_roi": 0.288,
    "trust_refunds": 0
  },
  {
    "wallet": "0xc684828f6b03487759ced2ebdd975f91f3532228",
    "name": "oliman2",
    "train_win": 77.3,
    "train_conv_roi": 0.173,
    "train_z": 3.83,
    "z_all": 4.05,
    "med_stake": 929,
    "avg_entry": 0.67,
    "train_n": 247,
    "fwd_win": 68.9,
    "fwd_conv_roi": -0.051,
    "fwd_n": 61,
    "conv_win": 66.2,
    "conv_won": 321,
    "conv_lost": 164,
    "conv_ref": 74,
    "conv_sold": 923,
    "conv_pnl": -67475,
    "conv30_win": 100.0,
    "conv30_won": 6,
    "conv30_lost": 0,
    "conv30_ref": 5,
    "conv30_sold": 91,
    "conv30_pnl": 15390,
    "realized_pnl": 40405,
    "all_win": 45.9,
    "all_won": 1942,
    "all_lost": 2288,
    "all_ref": 1072,
    "all_sold": 2107,
    "all_pnl": 20705,
    "open_pnl": -1593,
    "pm_pnl": 112699,
    "avg_bet": 1861,
    "copy_pnl": 2313,
    "held_pnl": 29,
    "held_won": 7,
    "held_lost": 2,
    "sold": 33,
    "last_trade": 1783539488,
    "last_conv_bet": 1783539488,
    "med_lead_h": 97.5,
    "trust_n": 120,
    "trust_wr": 0.783,
    "trust_roi": 0.194,
    "trust_refunds": 0
  },
  {
    "wallet": "0x0d42cc5ff0526fbb8f0bb9eafa9ebba3f23df124",
    "name": "42021",
    "train_win": 68.1,
    "train_conv_roi": 0.023,
    "train_z": 2.35,
    "z_all": 6.7,
    "med_stake": 446,
    "avg_entry": 0.64,
    "train_n": 386,
    "fwd_win": 71.9,
    "fwd_conv_roi": 0.115,
    "fwd_n": 57,
    "conv_win": 64.1,
    "conv_won": 252,
    "conv_lost": 141,
    "conv_ref": 9,
    "conv_sold": 997,
    "conv_pnl": 13663,
    "conv30_win": 100.0,
    "conv30_won": 6,
    "conv30_lost": 0,
    "conv30_ref": 0,
    "conv30_sold": 46,
    "conv30_pnl": 4115,
    "realized_pnl": 3741,
    "all_win": 36.5,
    "all_won": 1201,
    "all_lost": 2085,
    "all_ref": 93,
    "all_sold": 3612,
    "all_pnl": 25217,
    "open_pnl": -752,
    "pm_pnl": 25248,
    "avg_bet": 763,
    "copy_pnl": 1818,
    "held_pnl": 0,
    "held_won": 0,
    "held_lost": 0,
    "sold": 28,
    "last_trade": 1783521259,
    "last_conv_bet": 1783410734,
    "med_lead_h": 83.4,
    "trust_n": 214,
    "trust_wr": 0.729,
    "trust_roi": 0.094,
    "trust_refunds": 0
  },
  {
    "wallet": "0xe8ca3f758c93f44f3ec210542ab78afb7c0bcccb",
    "name": "Kruto2027",
    "train_win": 71.4,
    "train_conv_roi": 0.642,
    "train_z": 8.46,
    "z_all": 19.33,
    "med_stake": 308,
    "avg_entry": 0.47,
    "train_n": 259,
    "fwd_win": 77.0,
    "fwd_conv_roi": 0.457,
    "fwd_n": 61,
    "conv_win": 68.4,
    "conv_won": 52,
    "conv_lost": 24,
    "conv_ref": 30,
    "conv_sold": 194,
    "conv_pnl": 61990,
    "conv30_win": 72.7,
    "conv30_won": 8,
    "conv30_lost": 3,
    "conv30_ref": 0,
    "conv30_sold": 34,
    "conv30_pnl": 16442,
    "realized_pnl": 47548,
    "all_win": 58.8,
    "all_won": 329,
    "all_lost": 231,
    "all_ref": 84,
    "all_sold": 853,
    "all_pnl": 75839,
    "open_pnl": -162,
    "pm_pnl": 75851,
    "avg_bet": 759,
    "copy_pnl": 1285,
    "held_pnl": 256,
    "held_won": 11,
    "held_lost": 3,
    "sold": 37,
    "last_trade": 1783528964,
    "last_conv_bet": 1783475438,
    "med_lead_h": 76.1,
    "trust_n": 121,
    "trust_wr": 0.678,
    "trust_roi": 0.446,
    "trust_refunds": 9
  },
  {
    "wallet": "0xbadaf319415c17f28824a43ae0cd912b9d84d874",
    "name": null,
    "train_win": 76.5,
    "train_conv_roi": 0.455,
    "train_z": 3.54,
    "z_all": 4.67,
    "med_stake": 68,
    "avg_entry": 0.6,
    "train_n": 81,
    "fwd_win": 76.8,
    "fwd_conv_roi": 0.118,
    "fwd_n": 164,
    "conv_win": 79.4,
    "conv_won": 131,
    "conv_lost": 34,
    "conv_ref": 0,
    "conv_sold": 145,
    "conv_pnl": 6885,
    "conv30_win": 100.0,
    "conv30_won": 70,
    "conv30_lost": 0,
    "conv30_ref": 0,
    "conv30_sold": 136,
    "conv30_pnl": 6662,
    "realized_pnl": 5654,
    "all_win": 46.3,
    "all_won": 351,
    "all_lost": 407,
    "all_ref": 6,
    "all_sold": 783,
    "all_pnl": 13108,
    "open_pnl": 86,
    "pm_pnl": 12836,
    "avg_bet": 111,
    "copy_pnl": 1197,
    "held_pnl": 4,
    "held_won": 19,
    "held_lost": 5,
    "sold": 126,
    "last_trade": 1783540094,
    "last_conv_bet": 1783531133,
    "med_lead_h": 51.2,
    "trust_n": 201,
    "trust_wr": 0.801,
    "trust_roi": 0.279,
    "trust_refunds": 0
  },
  {
    "wallet": "0xe542afd3881c4c330ba0ebbb603bb470b2ba0a37",
    "name": "leegunner",
    "train_win": 68.2,
    "train_conv_roi": 0.378,
    "train_z": 7.98,
    "z_all": 14.51,
    "med_stake": 838,
    "avg_entry": 0.53,
    "train_n": 484,
    "fwd_win": 63.3,
    "fwd_conv_roi": 0.252,
    "fwd_n": 109,
    "conv_win": 88.3,
    "conv_won": 467,
    "conv_lost": 62,
    "conv_ref": 71,
    "conv_sold": 731,
    "conv_pnl": 204079,
    "conv30_win": 63.6,
    "conv30_won": 14,
    "conv30_lost": 8,
    "conv30_ref": 1,
    "conv30_sold": 65,
    "conv30_pnl": 10737,
    "realized_pnl": 66565,
    "all_win": 41.2,
    "all_won": 1789,
    "all_lost": 2555,
    "all_ref": 249,
    "all_sold": 2061,
    "all_pnl": 264137,
    "open_pnl": 10034,
    "pm_pnl": 345530,
    "avg_bet": 2307,
    "copy_pnl": 1075,
    "held_pnl": -257,
    "held_won": 0,
    "held_lost": 5,
    "sold": 24,
    "last_trade": 1783527419,
    "last_conv_bet": 1783510927,
    "med_lead_h": null,
    "trust_n": 263,
    "trust_wr": 0.665,
    "trust_roi": 0.213,
    "trust_refunds": 14
  },
  {
    "wallet": "0x41558102a796ba971c7567cad41c307e59f8fa41",
    "name": "LSB1",
    "train_win": 85.8,
    "train_conv_roi": 0.197,
    "train_z": 4.93,
    "z_all": 12.32,
    "med_stake": 342,
    "avg_entry": 0.75,
    "train_n": 302,
    "fwd_win": 90.2,
    "fwd_conv_roi": 0.173,
    "fwd_n": 245,
    "conv_win": 92.2,
    "conv_won": 365,
    "conv_lost": 31,
    "conv_ref": 0,
    "conv_sold": 50,
    "conv_pnl": 51191,
    "conv30_win": 95.6,
    "conv30_won": 175,
    "conv30_lost": 8,
    "conv30_ref": 0,
    "conv30_sold": 19,
    "conv30_pnl": 42375,
    "realized_pnl": 44291,
    "all_win": 92.1,
    "all_won": 1805,
    "all_lost": 154,
    "all_ref": 1,
    "all_sold": 269,
    "all_pnl": 76953,
    "open_pnl": 0,
    "pm_pnl": 74850,
    "avg_bet": 816,
    "copy_pnl": 903,
    "held_pnl": 1124,
    "held_won": 114,
    "held_lost": 8,
    "sold": 18,
    "last_trade": 1783536752,
    "last_conv_bet": 1783524767,
    "med_lead_h": 1.8,
    "trust_n": 413,
    "trust_wr": 0.879,
    "trust_roi": 0.168,
    "trust_refunds": 0
  },
  {
    "wallet": "0x82d2e4dbb0a849ff8e2f5380719769145648beea",
    "name": "lma0o0o0o",
    "train_win": 70.9,
    "train_conv_roi": 0.356,
    "train_z": 3.63,
    "z_all": 6.99,
    "med_stake": 2450,
    "avg_entry": 0.56,
    "train_n": 134,
    "fwd_win": 64.2,
    "fwd_conv_roi": 0.198,
    "fwd_n": 162,
    "conv_win": 69.4,
    "conv_won": 127,
    "conv_lost": 56,
    "conv_ref": 23,
    "conv_sold": 50,
    "conv_pnl": 136147,
    "conv30_win": 71.3,
    "conv30_won": 62,
    "conv30_lost": 25,
    "conv30_ref": 7,
    "conv30_sold": 30,
    "conv30_pnl": 58246,
    "realized_pnl": 58929,
    "all_win": 57.8,
    "all_won": 585,
    "all_lost": 427,
    "all_ref": 115,
    "all_sold": 149,
    "all_pnl": 165878,
    "open_pnl": -1113,
    "pm_pnl": 170485,
    "avg_bet": 3786,
    "copy_pnl": 826,
    "held_pnl": -480,
    "held_won": 4,
    "held_lost": 13,
    "sold": 47,
    "last_trade": 1783537547,
    "last_conv_bet": 1783535813,
    "med_lead_h": 6.3,
    "trust_n": 215,
    "trust_wr": 0.628,
    "trust_roi": 0.106,
    "trust_refunds": 17
  },
  {
    "wallet": "0xab417c0bacc9fe17368d5d662c957f54a1fcc453",
    "name": "earthisgood",
    "train_win": 70.0,
    "train_conv_roi": 0.107,
    "train_z": 3.21,
    "z_all": 2.24,
    "med_stake": 223,
    "avg_entry": 0.62,
    "train_n": 380,
    "fwd_win": 64.0,
    "fwd_conv_roi": 0.12,
    "fwd_n": 222,
    "conv_win": 63.2,
    "conv_won": 338,
    "conv_lost": 197,
    "conv_ref": 7,
    "conv_sold": 281,
    "conv_pnl": 12379,
    "conv30_win": 59.9,
    "conv30_won": 100,
    "conv30_lost": 67,
    "conv30_ref": 7,
    "conv30_sold": 81,
    "conv30_pnl": 2709,
    "realized_pnl": 1568,
    "all_win": 52.9,
    "all_won": 847,
    "all_lost": 754,
    "all_ref": 93,
    "all_sold": 2417,
    "all_pnl": 14443,
    "open_pnl": 0,
    "pm_pnl": 16727,
    "avg_bet": 240,
    "copy_pnl": 670,
    "held_pnl": 670,
    "held_won": 16,
    "held_lost": 19,
    "sold": 0,
    "last_trade": 1783460141,
    "last_conv_bet": 1783205636,
    "med_lead_h": 2.0,
    "trust_n": 325,
    "trust_wr": 0.708,
    "trust_roi": 0.164,
    "trust_refunds": 0
  },
  {
    "wallet": "0x215adbb63b47d0ca92f849fe2c2dc1adb0f6254c",
    "name": "BikesAreTheBikes",
    "train_win": 71.2,
    "train_conv_roi": 0.298,
    "train_z": 5.78,
    "z_all": 4.84,
    "med_stake": 392,
    "avg_entry": 0.57,
    "train_n": 299,
    "fwd_win": 56.6,
    "fwd_conv_roi": 0.34,
    "fwd_n": 274,
    "conv_win": 19.7,
    "conv_won": 24,
    "conv_lost": 98,
    "conv_ref": 29,
    "conv_sold": 1075,
    "conv_pnl": 45213,
    "conv30_win": 71.4,
    "conv30_won": 5,
    "conv30_lost": 2,
    "conv30_ref": 9,
    "conv30_sold": 301,
    "conv30_pnl": 61510,
    "realized_pnl": 59706,
    "all_win": 23.6,
    "all_won": 630,
    "all_lost": 2038,
    "all_ref": 508,
    "all_sold": 3019,
    "all_pnl": 64740,
    "open_pnl": 1777,
    "pm_pnl": 75116,
    "avg_bet": 694,
    "copy_pnl": 669,
    "held_pnl": 639,
    "held_won": 2,
    "held_lost": 0,
    "sold": 36,
    "last_trade": 1783537940,
    "last_conv_bet": 1783529116,
    "med_lead_h": 76.4,
    "trust_n": 305,
    "trust_wr": 0.741,
    "trust_roi": 0.388,
    "trust_refunds": 0
  },
  {
    "wallet": "0xa1d57d329227c75b12b09f927fb3d6d6ef8f1343",
    "name": "1kto1m",
    "train_win": 74.8,
    "train_conv_roi": 0.178,
    "train_z": 2.7,
    "z_all": 2.4,
    "med_stake": 488,
    "avg_entry": 0.66,
    "train_n": 139,
    "fwd_win": 74.4,
    "fwd_conv_roi": 0.243,
    "fwd_n": 156,
    "conv_win": 97.7,
    "conv_won": 86,
    "conv_lost": 2,
    "conv_ref": 1,
    "conv_sold": 178,
    "conv_pnl": 21510,
    "conv30_win": 100.0,
    "conv30_won": 23,
    "conv30_lost": 0,
    "conv30_ref": 1,
    "conv30_sold": 82,
    "conv30_pnl": 9188,
    "realized_pnl": 15139,
    "all_win": 65.9,
    "all_won": 306,
    "all_lost": 158,
    "all_ref": 7,
    "all_sold": 864,
    "all_pnl": 32311,
    "open_pnl": 0,
    "pm_pnl": 32305,
    "avg_bet": 797,
    "copy_pnl": 629,
    "held_pnl": 16,
    "held_won": 3,
    "held_lost": 0,
    "sold": 105,
    "last_trade": 1783521917,
    "last_conv_bet": 1783521370,
    "med_lead_h": 9.0,
    "trust_n": 261,
    "trust_wr": 0.774,
    "trust_roi": 0.237,
    "trust_refunds": 0
  },
  {
    "wallet": "0x2f9b8638f03af7d6053c512cc054ac733489a68c",
    "name": "fgfkjytyjt",
    "train_win": 84.6,
    "train_conv_roi": 2.873,
    "train_z": 4.4,
    "z_all": 2.55,
    "med_stake": 97,
    "avg_entry": 0.32,
    "train_n": 13,
    "fwd_win": 55.6,
    "fwd_conv_roi": 0.333,
    "fwd_n": 9,
    "conv_win": 62.5,
    "conv_won": 5,
    "conv_lost": 3,
    "conv_ref": 0,
    "conv_sold": 20,
    "conv_pnl": 5485,
    "conv30_win": 100.0,
    "conv30_won": 1,
    "conv30_lost": 0,
    "conv30_ref": 0,
    "conv30_sold": 8,
    "conv30_pnl": 1079,
    "realized_pnl": 6407,
    "all_win": 45.7,
    "all_won": 21,
    "all_lost": 25,
    "all_ref": 2,
    "all_sold": 88,
    "all_pnl": 6407,
    "open_pnl": 84,
    "pm_pnl": 8873,
    "avg_bet": 163,
    "copy_pnl": 567,
    "held_pnl": -35,
    "held_won": 3,
    "held_lost": 5,
    "sold": 4,
    "last_trade": 1783499951,
    "last_conv_bet": 1783465583,
    "med_lead_h": 32.2,
    "trust_n": 20,
    "trust_wr": 0.7,
    "trust_roi": 1.481,
    "trust_refunds": 0
  },
  {
    "wallet": "0xf6099a9eacfef24a4161bd857fbfbcd36cdfe68b",
    "name": "Xixihaha008",
    "train_win": 82.2,
    "train_conv_roi": 0.275,
    "train_z": 3.88,
    "z_all": 3.49,
    "med_stake": 60,
    "avg_entry": 0.65,
    "train_n": 90,
    "fwd_win": 75.7,
    "fwd_conv_roi": 0.122,
    "fwd_n": 259,
    "conv_win": 89.8,
    "conv_won": 88,
    "conv_lost": 10,
    "conv_ref": 9,
    "conv_sold": 570,
    "conv_pnl": 1210,
    "conv30_win": 96.2,
    "conv30_won": 25,
    "conv30_lost": 1,
    "conv30_ref": 2,
    "conv30_sold": 297,
    "conv30_pnl": 1614,
    "realized_pnl": 1806,
    "all_win": 36.0,
    "all_won": 293,
    "all_lost": 520,
    "all_ref": 39,
    "all_sold": 2529,
    "all_pnl": 3253,
    "open_pnl": 123,
    "pm_pnl": 3936,
    "avg_bet": 143,
    "copy_pnl": 496,
    "held_pnl": 7,
    "held_won": 7,
    "held_lost": 1,
    "sold": 153,
    "last_trade": 1783539809,
    "last_conv_bet": 1783474753,
    "med_lead_h": 156.8,
    "trust_n": 293,
    "trust_wr": 0.775,
    "trust_roi": 0.17,
    "trust_refunds": 3
  },
  {
    "wallet": "0x13464aabec792c36b062316f474713e681330448",
    "name": "Winnertraders",
    "train_win": 70.2,
    "train_conv_roi": 0.155,
    "train_z": 3.88,
    "z_all": 8.31,
    "med_stake": 167,
    "avg_entry": 0.62,
    "train_n": 346,
    "fwd_win": 66.3,
    "fwd_conv_roi": 0.194,
    "fwd_n": 104,
    "conv_win": 79.0,
    "conv_won": 83,
    "conv_lost": 22,
    "conv_ref": 2,
    "conv_sold": 409,
    "conv_pnl": 8365,
    "conv30_win": 64.3,
    "conv30_won": 9,
    "conv30_lost": 5,
    "conv30_ref": 0,
    "conv30_sold": 64,
    "conv30_pnl": 1909,
    "realized_pnl": 5883,
    "all_win": 32.2,
    "all_won": 155,
    "all_lost": 326,
    "all_ref": 19,
    "all_sold": 2079,
    "all_pnl": 13205,
    "open_pnl": 103,
    "pm_pnl": 14063,
    "avg_bet": 201,
    "copy_pnl": 472,
    "held_pnl": -51,
    "held_won": 0,
    "held_lost": 1,
    "sold": 58,
    "last_trade": 1783535095,
    "last_conv_bet": 1783519391,
    "med_lead_h": 157.2,
    "trust_n": 194,
    "trust_wr": 0.732,
    "trust_roi": 0.16,
    "trust_refunds": 2
  },
  {
    "wallet": "0xd7d36345c4aab150e59577e360696b01d01d698b",
    "name": "gkmgkldfmg",
    "train_win": 71.9,
    "train_conv_roi": 0.21,
    "train_z": 2.24,
    "z_all": 2.05,
    "med_stake": 293,
    "avg_entry": 0.59,
    "train_n": 64,
    "fwd_win": 61.3,
    "fwd_conv_roi": 0.14,
    "fwd_n": 191,
    "conv_win": 71.9,
    "conv_won": 41,
    "conv_lost": 16,
    "conv_ref": 1,
    "conv_sold": 81,
    "conv_pnl": 17992,
    "conv30_win": 100.0,
    "conv30_won": 23,
    "conv30_lost": 0,
    "conv30_ref": 1,
    "conv30_sold": 55,
    "conv30_pnl": 17030,
    "realized_pnl": 57794,
    "all_win": 59.8,
    "all_won": 286,
    "all_lost": 192,
    "all_ref": 2,
    "all_sold": 214,
    "all_pnl": 28156,
    "open_pnl": -171,
    "pm_pnl": 28491,
    "avg_bet": 853,
    "copy_pnl": 343,
    "held_pnl": -101,
    "held_won": 0,
    "held_lost": 2,
    "sold": 70,
    "last_trade": 1783537490,
    "last_conv_bet": 1783537291,
    "med_lead_h": 8.4,
    "trust_n": 123,
    "trust_wr": 0.659,
    "trust_roi": 0.165,
    "trust_refunds": 3
  },
  {
    "wallet": "0x72e1597864456eda62878413cf3e60c332e4a45d",
    "name": "ArbTraderRookie",
    "train_win": 99.1,
    "train_conv_roi": 0.97,
    "train_z": 17.92,
    "z_all": 29.09,
    "med_stake": 424,
    "avg_entry": 0.52,
    "train_n": 336,
    "fwd_win": 99.4,
    "fwd_conv_roi": 1.083,
    "fwd_n": 179,
    "conv_win": 98.7,
    "conv_won": 303,
    "conv_lost": 4,
    "conv_ref": 321,
    "conv_sold": 41,
    "conv_pnl": 6399,
    "conv30_win": 0.0,
    "conv30_won": 0,
    "conv30_lost": 1,
    "conv30_ref": 102,
    "conv30_sold": 8,
    "conv30_pnl": 5947,
    "realized_pnl": 11352,
    "all_win": 99.0,
    "all_won": 2062,
    "all_lost": 20,
    "all_ref": 1150,
    "all_sold": 112,
    "all_pnl": 9081,
    "open_pnl": 0,
    "pm_pnl": 9080,
    "avg_bet": 1064,
    "copy_pnl": 336,
    "held_pnl": 136,
    "held_won": 0,
    "held_lost": 0,
    "sold": 34,
    "last_trade": 1783536655,
    "last_conv_bet": 1783474384,
    "med_lead_h": 161.2,
    "trust_n": 13,
    "trust_wr": 0.846,
    "trust_roi": 0.065,
    "trust_refunds": 236
  },
  {
    "wallet": "0x69b9bd4fa27813091fcfe726541f2fd7baa3a5d5",
    "name": "Coteykens",
    "train_win": 69.9,
    "train_conv_roi": 0.308,
    "train_z": 3.93,
    "z_all": 3.53,
    "med_stake": 212,
    "avg_entry": 0.55,
    "train_n": 153,
    "fwd_win": 61.6,
    "fwd_conv_roi": 0.119,
    "fwd_n": 73,
    "conv_win": 65.5,
    "conv_won": 135,
    "conv_lost": 71,
    "conv_ref": 0,
    "conv_sold": 3,
    "conv_pnl": 10826,
    "conv30_win": 100.0,
    "conv30_won": 16,
    "conv30_lost": 0,
    "conv30_ref": 0,
    "conv30_sold": 1,
    "conv30_pnl": 4087,
    "realized_pnl": 53923,
    "all_win": 58.0,
    "all_won": 585,
    "all_lost": 424,
    "all_ref": 4,
    "all_sold": 19,
    "all_pnl": 14480,
    "open_pnl": 0,
    "pm_pnl": 14420,
    "avg_bet": 307,
    "copy_pnl": 317,
    "held_pnl": -634,
    "held_won": 5,
    "held_lost": 16,
    "sold": 22,
    "last_trade": 1781536882,
    "last_conv_bet": 1781455797,
    "med_lead_h": 153.1,
    "trust_n": 207,
    "trust_wr": 0.652,
    "trust_roi": 0.222,
    "trust_refunds": 0
  },
  {
    "wallet": "0xa9aca75fb5d8f04c2ec9eeb0eb0c30d2e526c5d1",
    "name": "suraxy",
    "train_win": 65.9,
    "train_conv_roi": 0.114,
    "train_z": 2.77,
    "z_all": 2.67,
    "med_stake": 1410,
    "avg_entry": 0.59,
    "train_n": 255,
    "fwd_win": 63.3,
    "fwd_conv_roi": 0.271,
    "fwd_n": 166,
    "conv_win": 73.5,
    "conv_won": 50,
    "conv_lost": 18,
    "conv_ref": 3,
    "conv_sold": 396,
    "conv_pnl": 83756,
    "conv30_win": 53.8,
    "conv30_won": 7,
    "conv30_lost": 6,
    "conv30_ref": 1,
    "conv30_sold": 137,
    "conv30_pnl": 9461,
    "realized_pnl": 804,
    "all_win": 23.7,
    "all_won": 211,
    "all_lost": 678,
    "all_ref": 12,
    "all_sold": 1433,
    "all_pnl": 57620,
    "open_pnl": 1493,
    "pm_pnl": 57139,
    "avg_bet": 3179,
    "copy_pnl": 217,
    "held_pnl": 55,
    "held_won": 3,
    "held_lost": 0,
    "sold": 64,
    "last_trade": 1783539844,
    "last_conv_bet": 1783450291,
    "med_lead_h": 29.1,
    "trust_n": 231,
    "trust_wr": 0.68,
    "trust_roi": 0.266,
    "trust_refunds": 0
  },
  {
    "wallet": "0xed61f86bb5298d2f27c21c433ce58d80b88a9aa3",
    "name": "ewww1",
    "train_win": 73.1,
    "train_conv_roi": 0.137,
    "train_z": 3.04,
    "z_all": 10.28,
    "med_stake": 1305,
    "avg_entry": 0.66,
    "train_n": 305,
    "fwd_win": 85.7,
    "fwd_conv_roi": 0.156,
    "fwd_n": 21,
    "conv_win": 93.1,
    "conv_won": 54,
    "conv_lost": 4,
    "conv_ref": 1,
    "conv_sold": 759,
    "conv_pnl": 230769,
    "conv30_win": 100.0,
    "conv30_won": 3,
    "conv30_lost": 0,
    "conv30_ref": 0,
    "conv30_sold": 4,
    "conv30_pnl": 1186,
    "realized_pnl": 28147,
    "all_win": 91.2,
    "all_won": 341,
    "all_lost": 33,
    "all_ref": 66,
    "all_sold": 3648,
    "all_pnl": 409101,
    "open_pnl": 0,
    "pm_pnl": 409401,
    "avg_bet": 1519,
    "copy_pnl": 208,
    "held_pnl": -36,
    "held_won": 2,
    "held_lost": 2,
    "sold": 18,
    "last_trade": 1783304591,
    "last_conv_bet": 1782345065,
    "med_lead_h": 2.1,
    "trust_n": 61,
    "trust_wr": 0.754,
    "trust_roi": 0.231,
    "trust_refunds": 0
  },
  {
    "wallet": "0x86c878cde72660ec52f5e6f0f0438b76de8fc867",
    "name": "fortuneking",
    "train_win": 76.4,
    "train_conv_roi": 0.113,
    "train_z": 3.13,
    "z_all": 8.05,
    "med_stake": 1690,
    "avg_entry": 0.69,
    "train_n": 313,
    "fwd_win": 70.6,
    "fwd_conv_roi": 0.104,
    "fwd_n": 136,
    "conv_win": 74.1,
    "conv_won": 304,
    "conv_lost": 106,
    "conv_ref": 3,
    "conv_sold": 24,
    "conv_pnl": 79404,
    "conv30_win": 67.0,
    "conv30_won": 69,
    "conv30_lost": 34,
    "conv30_ref": 0,
    "conv30_sold": 6,
    "conv30_pnl": 3370,
    "realized_pnl": 60215,
    "all_win": 62.7,
    "all_won": 1260,
    "all_lost": 749,
    "all_ref": 29,
    "all_sold": 144,
    "all_pnl": 136276,
    "open_pnl": 4,
    "pm_pnl": 136436,
    "avg_bet": 2789,
    "copy_pnl": 201,
    "held_pnl": 189,
    "held_won": 64,
    "held_lost": 21,
    "sold": 3,
    "last_trade": 1783526912,
    "last_conv_bet": 1783461592,
    "med_lead_h": 155.9,
    "trust_n": 249,
    "trust_wr": 0.739,
    "trust_roi": 0.071,
    "trust_refunds": 0
  },
  {
    "wallet": "0xfb129bebeda3b049b984ef1965cf69d9806cd1b3",
    "name": "Predict90",
    "train_win": 65.9,
    "train_conv_roi": 0.097,
    "train_z": 2.4,
    "z_all": 2.27,
    "med_stake": 100,
    "avg_entry": 0.57,
    "train_n": 129,
    "fwd_win": 56.2,
    "fwd_conv_roi": 0.137,
    "fwd_n": 146,
    "conv_win": 44.6,
    "conv_won": 58,
    "conv_lost": 72,
    "conv_ref": 1,
    "conv_sold": 212,
    "conv_pnl": -1366,
    "conv30_win": 100.0,
    "conv30_won": 9,
    "conv30_lost": 0,
    "conv30_ref": 1,
    "conv30_sold": 53,
    "conv30_pnl": 1910,
    "realized_pnl": 7001,
    "all_win": 15.1,
    "all_won": 170,
    "all_lost": 959,
    "all_ref": 1,
    "all_sold": 583,
    "all_pnl": -3207,
    "open_pnl": -62,
    "pm_pnl": -4379,
    "avg_bet": 216,
    "copy_pnl": 199,
    "held_pnl": -680,
    "held_won": 3,
    "held_lost": 15,
    "sold": 89,
    "last_trade": 1783507381,
    "last_conv_bet": 1783507381,
    "med_lead_h": 10.3,
    "trust_n": 153,
    "trust_wr": 0.66,
    "trust_roi": 0.146,
    "trust_refunds": 0
  },
  {
    "wallet": "0xe0a2f29b1fadb2259111bbeca392d3805ec4a349",
    "name": "Marty-Byrde",
    "train_win": 66.1,
    "train_conv_roi": 0.082,
    "train_z": 1.93,
    "z_all": 3.41,
    "med_stake": 622,
    "avg_entry": 0.6,
    "train_n": 180,
    "fwd_win": 60.7,
    "fwd_conv_roi": -0.093,
    "fwd_n": 56,
    "conv_win": 94.8,
    "conv_won": 92,
    "conv_lost": 5,
    "conv_ref": 0,
    "conv_sold": 691,
    "conv_pnl": 4865,
    "conv30_win": 100.0,
    "conv30_won": 4,
    "conv30_lost": 0,
    "conv30_ref": 0,
    "conv30_sold": 69,
    "conv30_pnl": 845,
    "realized_pnl": -1941,
    "all_win": 49.9,
    "all_won": 265,
    "all_lost": 266,
    "all_ref": 50,
    "all_sold": 3359,
    "all_pnl": -941,
    "open_pnl": 171,
    "pm_pnl": -535,
    "avg_bet": 1251,
    "copy_pnl": 152,
    "held_pnl": 0,
    "held_won": 0,
    "held_lost": 0,
    "sold": 26,
    "last_trade": 1783541135,
    "last_conv_bet": 1783538840,
    "med_lead_h": 95.4,
    "trust_n": 107,
    "trust_wr": 0.701,
    "trust_roi": 0.015,
    "trust_refunds": 0
  },
  {
    "wallet": "0x40ce68f1564f3c751b12d88a393d8cc0651dbf90",
    "name": "JuiceFarm",
    "train_win": 75.5,
    "train_conv_roi": 0.101,
    "train_z": 2.31,
    "z_all": 2.8,
    "med_stake": 900,
    "avg_entry": 0.7,
    "train_n": 318,
    "fwd_win": 57.1,
    "fwd_conv_roi": -0.049,
    "fwd_n": 161,
    "conv_win": 69.1,
    "conv_won": 248,
    "conv_lost": 111,
    "conv_ref": 3,
    "conv_sold": 2,
    "conv_pnl": 4523,
    "conv30_win": 100.0,
    "conv30_won": 31,
    "conv30_lost": 0,
    "conv30_ref": 0,
    "conv30_sold": 1,
    "conv30_pnl": 16840,
    "realized_pnl": 241335,
    "all_win": 57.5,
    "all_won": 1038,
    "all_lost": 768,
    "all_ref": 7,
    "all_sold": 6,
    "all_pnl": 31104,
    "open_pnl": -700,
    "pm_pnl": 34411,
    "avg_bet": 1043,
    "copy_pnl": 105,
    "held_pnl": 103,
    "held_won": 37,
    "held_lost": 11,
    "sold": 1,
    "last_trade": 1783525984,
    "last_conv_bet": 1783525240,
    "med_lead_h": 30.4,
    "trust_n": 335,
    "trust_wr": 0.687,
    "trust_roi": 0.015,
    "trust_refunds": 2
  },
  {
    "wallet": "0x921433c93558b9a4ba807ec824d02aad7ea2ddbf",
    "name": "AIcAIc",
    "train_win": 67.6,
    "train_conv_roi": 0.415,
    "train_z": 2.01,
    "z_all": 3.27,
    "med_stake": 171,
    "avg_entry": 0.52,
    "train_n": 34,
    "fwd_win": 63.5,
    "fwd_conv_roi": 0.121,
    "fwd_n": 189,
    "conv_win": 66.7,
    "conv_won": 18,
    "conv_lost": 9,
    "conv_ref": 0,
    "conv_sold": 57,
    "conv_pnl": 1675,
    "conv30_win": 61.1,
    "conv30_won": 11,
    "conv30_lost": 7,
    "conv30_ref": 0,
    "conv30_sold": 39,
    "conv30_pnl": -3341,
    "realized_pnl": 1393,
    "all_win": 42.4,
    "all_won": 64,
    "all_lost": 87,
    "all_ref": 0,
    "all_sold": 267,
    "all_pnl": 1393,
    "open_pnl": 0,
    "pm_pnl": 1393,
    "avg_bet": 798,
    "copy_pnl": 99,
    "held_pnl": -303,
    "held_won": 0,
    "held_lost": 6,
    "sold": 48,
    "last_trade": 1783501096,
    "last_conv_bet": 1783494770,
    "med_lead_h": 2.1,
    "trust_n": 76,
    "trust_wr": 0.75,
    "trust_roi": 0.182,
    "trust_refunds": 2
  },
  {
    "wallet": "0xfc81760d44a21acc9fd4b749a5bf9a9b2eeae072",
    "name": "iohihoo",
    "train_win": 88.5,
    "train_conv_roi": 0.612,
    "train_z": 7.89,
    "z_all": 7.91,
    "med_stake": 80,
    "avg_entry": 0.63,
    "train_n": 183,
    "fwd_win": 91.7,
    "fwd_conv_roi": 0.759,
    "fwd_n": 60,
    "conv_win": 86.8,
    "conv_won": 46,
    "conv_lost": 7,
    "conv_ref": 100,
    "conv_sold": 78,
    "conv_pnl": 1392,
    "conv30_win": 66.7,
    "conv30_won": 6,
    "conv30_lost": 3,
    "conv30_ref": 29,
    "conv30_sold": 9,
    "conv30_pnl": -231,
    "realized_pnl": 429,
    "all_win": 76.5,
    "all_won": 414,
    "all_lost": 127,
    "all_ref": 233,
    "all_sold": 377,
    "all_pnl": 1420,
    "open_pnl": 34,
    "pm_pnl": 1459,
    "avg_bet": 117,
    "copy_pnl": 96,
    "held_pnl": -7,
    "held_won": 1,
    "held_lost": 1,
    "sold": 5,
    "last_trade": 1783430785,
    "last_conv_bet": 1782989332,
    "med_lead_h": 161.7,
    "trust_n": 42,
    "trust_wr": 0.714,
    "trust_roi": 0.005,
    "trust_refunds": 84
  },
  {
    "wallet": "0x73afc8160c17830c0c7281a7bf570c871455b880",
    "name": "0xb0E43B885657a33B347A4af1D05Bd5f3c3A7E99",
    "train_win": 84.9,
    "train_conv_roi": 0.737,
    "train_z": 7.17,
    "z_all": 20.16,
    "med_stake": 2350,
    "avg_entry": 0.53,
    "train_n": 106,
    "fwd_win": 100.0,
    "fwd_conv_roi": 1.202,
    "fwd_n": 89,
    "conv_win": 69.6,
    "conv_won": 16,
    "conv_lost": 7,
    "conv_ref": 144,
    "conv_sold": 35,
    "conv_pnl": 177393,
    "conv30_win": null,
    "conv30_won": 0,
    "conv30_lost": 0,
    "conv30_ref": 61,
    "conv30_sold": 12,
    "conv30_pnl": 82271,
    "realized_pnl": 165578,
    "all_win": 71.0,
    "all_won": 76,
    "all_lost": 31,
    "all_ref": 800,
    "all_sold": 103,
    "all_pnl": 218523,
    "open_pnl": 0,
    "pm_pnl": 218822,
    "avg_bet": 7305,
    "copy_pnl": 87,
    "held_pnl": 60,
    "held_won": 0,
    "held_lost": 0,
    "sold": 10,
    "last_trade": 1783527668,
    "last_conv_bet": 1783428709,
    "med_lead_h": 162.0,
    "trust_n": 20,
    "trust_wr": 0.65,
    "trust_roi": 0.089,
    "trust_refunds": 142
  },
  {
    "wallet": "0x1cff72c8dddc30a64486fda6eab71ab5f9243984",
    "name": "sng888",
    "train_win": 79.2,
    "train_conv_roi": 0.207,
    "train_z": 3.0,
    "z_all": 5.42,
    "med_stake": 220,
    "avg_entry": 0.66,
    "train_n": 106,
    "fwd_win": 74.2,
    "fwd_conv_roi": 0.122,
    "fwd_n": 31,
    "conv_win": 70.8,
    "conv_won": 75,
    "conv_lost": 31,
    "conv_ref": 13,
    "conv_sold": 10,
    "conv_pnl": 452,
    "conv30_win": 94.1,
    "conv30_won": 16,
    "conv30_lost": 1,
    "conv30_ref": 1,
    "conv30_sold": 1,
    "conv30_pnl": 1757,
    "realized_pnl": 13511,
    "all_win": 54.2,
    "all_won": 289,
    "all_lost": 244,
    "all_ref": 56,
    "all_sold": 53,
    "all_pnl": 1206,
    "open_pnl": -18,
    "pm_pnl": 1403,
    "avg_bet": 266,
    "copy_pnl": 86,
    "held_pnl": 75,
    "held_won": 14,
    "held_lost": 7,
    "sold": 4,
    "last_trade": 1783532524,
    "last_conv_bet": 1783518935,
    "med_lead_h": 14.2,
    "trust_n": 65,
    "trust_wr": 0.677,
    "trust_roi": 0.012,
    "trust_refunds": 8
  },
  {
    "wallet": "0x460d15ce9258fb8ce6a94d984574598d2f1c9d5f",
    "name": "0x460D15cE9258FB8cE6A94D984574598D2f1c9d5F-1759848102153",
    "train_win": 72.5,
    "train_conv_roi": 0.283,
    "train_z": 2.96,
    "z_all": 6.08,
    "med_stake": 103,
    "avg_entry": 0.59,
    "train_n": 91,
    "fwd_win": 63.6,
    "fwd_conv_roi": 0.259,
    "fwd_n": 11,
    "conv_win": 69.9,
    "conv_won": 51,
    "conv_lost": 22,
    "conv_ref": 6,
    "conv_sold": 18,
    "conv_pnl": 2202,
    "conv30_win": 100.0,
    "conv30_won": 5,
    "conv30_lost": 0,
    "conv30_ref": 0,
    "conv30_sold": 1,
    "conv30_pnl": 784,
    "realized_pnl": 2918,
    "all_win": 59.7,
    "all_won": 247,
    "all_lost": 167,
    "all_ref": 9,
    "all_sold": 58,
    "all_pnl": 2918,
    "open_pnl": 0,
    "pm_pnl": 2919,
    "avg_bet": 182,
    "copy_pnl": 46,
    "held_pnl": 39,
    "held_won": 3,
    "held_lost": 3,
    "sold": 3,
    "last_trade": 1782910820,
    "last_conv_bet": 1782876154,
    "med_lead_h": 148.2,
    "trust_n": 36,
    "trust_wr": 0.667,
    "trust_roi": 0.512,
    "trust_refunds": 0
  },
  {
    "wallet": "0xb8f6c79e452d7247d0cf47d16eaf7911953c4f7f",
    "name": "sweise",
    "train_win": 68.6,
    "train_conv_roi": 0.124,
    "train_z": 2.45,
    "z_all": 3.37,
    "med_stake": 68,
    "avg_entry": 0.63,
    "train_n": 344,
    "fwd_win": 83.3,
    "fwd_conv_roi": 0.118,
    "fwd_n": 138,
    "conv_win": 73.9,
    "conv_won": 291,
    "conv_lost": 103,
    "conv_ref": 26,
    "conv_sold": 4,
    "conv_pnl": 2940,
    "conv30_win": 86.9,
    "conv30_won": 73,
    "conv30_lost": 11,
    "conv30_ref": 10,
    "conv30_sold": 3,
    "conv30_pnl": 1099,
    "realized_pnl": 3244,
    "all_win": 54.5,
    "all_won": 1085,
    "all_lost": 906,
    "all_ref": 53,
    "all_sold": 76,
    "all_pnl": 3157,
    "open_pnl": -61,
    "pm_pnl": 3096,
    "avg_bet": 107,
    "copy_pnl": 31,
    "held_pnl": 54,
    "held_won": 47,
    "held_lost": 7,
    "sold": 3,
    "last_trade": 1783534006,
    "last_conv_bet": 1783455287,
    "med_lead_h": 150.7,
    "trust_n": 138,
    "trust_wr": 0.819,
    "trust_roi": 0.079,
    "trust_refunds": 21
  },
  {
    "wallet": "0xed37e7316f6b1b99da8893e0c09cfe0bf1b62f93",
    "name": "0xed37E7316F6b1B99da8893E0C09Cfe0Bf1B62F93-1770305278633",
    "train_win": 82.9,
    "train_conv_roi": 0.247,
    "train_z": 2.32,
    "z_all": 3.38,
    "med_stake": 165,
    "avg_entry": 0.65,
    "train_n": 35,
    "fwd_win": 82.4,
    "fwd_conv_roi": 1.024,
    "fwd_n": 17,
    "conv_win": 57.1,
    "conv_won": 4,
    "conv_lost": 3,
    "conv_ref": 2,
    "conv_sold": 32,
    "conv_pnl": 1368,
    "conv30_win": 100.0,
    "conv30_won": 1,
    "conv30_lost": 0,
    "conv30_ref": 0,
    "conv30_sold": 12,
    "conv30_pnl": 500,
    "realized_pnl": 1388,
    "all_win": 43.3,
    "all_won": 42,
    "all_lost": 55,
    "all_ref": 2,
    "all_sold": 105,
    "all_pnl": 1388,
    "open_pnl": 0,
    "pm_pnl": 1914,
    "avg_bet": 454,
    "copy_pnl": 27,
    "held_pnl": 0,
    "held_won": 0,
    "held_lost": 0,
    "sold": 8,
    "last_trade": 1782913988,
    "last_conv_bet": 1782754403,
    "med_lead_h": null,
    "trust_n": 36,
    "trust_wr": 0.889,
    "trust_roi": 0.337,
    "trust_refunds": 0
  },
  {
    "wallet": "0x809205fb1c91f746b9703ca412c4fdd0435db8a2",
    "name": "just-hanging-around",
    "train_win": 76.6,
    "train_conv_roi": 0.053,
    "train_z": 1.93,
    "z_all": 3.05,
    "med_stake": 97,
    "avg_entry": 0.73,
    "train_n": 261,
    "fwd_win": 77.8,
    "fwd_conv_roi": 0.082,
    "fwd_n": 27,
    "conv_win": 86.4,
    "conv_won": 114,
    "conv_lost": 18,
    "conv_ref": 6,
    "conv_sold": 234,
    "conv_pnl": 99,
    "conv30_win": 100.0,
    "conv30_won": 9,
    "conv30_lost": 0,
    "conv30_ref": 2,
    "conv30_sold": 7,
    "conv30_pnl": 142,
    "realized_pnl": 173,
    "all_win": 56.9,
    "all_won": 574,
    "all_lost": 435,
    "all_ref": 13,
    "all_sold": 834,
    "all_pnl": -1135,
    "open_pnl": 163,
    "pm_pnl": -893,
    "avg_bet": 234,
    "copy_pnl": 14,
    "held_pnl": 3,
    "held_won": 2,
    "held_lost": 0,
    "sold": 19,
    "last_trade": 1783541077,
    "last_conv_bet": 1783534001,
    "med_lead_h": 559.5,
    "trust_n": 55,
    "trust_wr": 0.891,
    "trust_roi": 0.077,
    "trust_refunds": 0
  },
  {
    "wallet": "0x1aeebd7b0eb92037a630004f8eabc0759c36c139",
    "name": "KBO30",
    "train_win": 79.3,
    "train_conv_roi": 0.148,
    "train_z": 2.76,
    "z_all": 2.15,
    "med_stake": 4423,
    "avg_entry": 0.68,
    "train_n": 87,
    "fwd_win": 78.3,
    "fwd_conv_roi": -0.063,
    "fwd_n": 23,
    "conv_win": 93.7,
    "conv_won": 59,
    "conv_lost": 4,
    "conv_ref": 1,
    "conv_sold": 135,
    "conv_pnl": 37604,
    "conv30_win": 90.9,
    "conv30_won": 10,
    "conv30_lost": 1,
    "conv30_ref": 0,
    "conv30_sold": 6,
    "conv30_pnl": -9381,
    "realized_pnl": 67038,
    "all_win": 52.9,
    "all_won": 282,
    "all_lost": 251,
    "all_ref": 6,
    "all_sold": 456,
    "all_pnl": 91479,
    "open_pnl": 2980,
    "pm_pnl": 95249,
    "avg_bet": 7025,
    "copy_pnl": 12,
    "held_pnl": -124,
    "held_won": 5,
    "held_lost": 3,
    "sold": 9,
    "last_trade": 1783536161,
    "last_conv_bet": 1783465004,
    "med_lead_h": 160.2,
    "trust_n": 59,
    "trust_wr": 0.831,
    "trust_roi": 0.199,
    "trust_refunds": 0
  },
  {
    "wallet": "0x83d9c8fe37f1b5141f3219219403d87f4513651b",
    "name": "4buc0",
    "train_win": 71.8,
    "train_conv_roi": 0.132,
    "train_z": 2.19,
    "z_all": 2.14,
    "med_stake": 2245,
    "avg_entry": 0.66,
    "train_n": 174,
    "fwd_win": null,
    "fwd_conv_roi": null,
    "fwd_n": 1,
    "conv_win": 90.8,
    "conv_won": 207,
    "conv_lost": 21,
    "conv_ref": 0,
    "conv_sold": 252,
    "conv_pnl": 192670,
    "conv30_win": null,
    "conv30_won": 0,
    "conv30_lost": 0,
    "conv30_ref": 0,
    "conv30_sold": 0,
    "conv30_pnl": 0,
    "realized_pnl": 193522,
    "all_win": 64.0,
    "all_won": 655,
    "all_lost": 368,
    "all_ref": 3,
    "all_sold": 1377,
    "all_pnl": 236507,
    "open_pnl": 0,
    "pm_pnl": 240984,
    "avg_bet": 4979,
    "copy_pnl": 4,
    "held_pnl": 4,
    "held_won": 1,
    "held_lost": 0,
    "sold": 0,
    "last_trade": 1780951776,
    "last_conv_bet": 1780951776,
    "med_lead_h": 34.5,
    "trust_n": 99,
    "trust_wr": 0.747,
    "trust_roi": 0.189,
    "trust_refunds": 0
  }
]